{"name":"Don´t Crush My Castle","tagline":"Next-Gen Tower Defense","body":"Welcome to Don´t Crush my Castle\r\n================================\r\nDon't Crush my Castle (DCmC) is an open-source and highly-customizable tower defense (currently at _alpha 0.7 version_ with a lot of juicy stuff that will be included in the future by some of DCmC contributors to make it a next-gen of tower-defense games\r\n\r\n![DCmC alpha 0.6 screenshot](https://cloud.githubusercontent.com/assets/5960567/6384307/1d816f8e-bd5b-11e4-8133-31ed7dea97ff.jpg)    \r\n_DCmC alpha 0.6 screenshot_\r\n\r\nDon't Crush My Castle is being developed in C++ and [Allegro 5](https://github.com/liballeg/allegro5) and [Tiled](https://github.com/bjorn/tiled)\r\n\r\nIs DCmC working currently?    \r\n[![Build Status](https://travis-ci.org/demiurgosoft/dont-crush-my-castle.svg?branch=master)](https://travis-ci.org/demiurgosoft/dont-crush-my-castle)\r\n\r\nTo get all the information about DCmC project don't forget to **[Check Don't Crush My Castle Wiki](https://github.com/demiurgosoft/dont-crush-my-castle/wiki)**\r\n\r\nThis project participates in the following contests:    \r\n* CUSL - http://www.concursosoftwarelibre.org/1415/?q=proyectos     \r\n* Certamen de Proyectos Libres de la UGR - http://osl.ugr.es/2014/09/26/premios-a-proyectos-libres-de-la-ugr/  \r\n\r\n###Find Don't Crush My Castle on:\r\n\r\n* GitHub - https://github.com/demiurgosoft/dont-crush-my-castle\r\n* GitHubPages - http://demiurgosoft.github.io/dont-crush-my-castle/\r\n* GitHub Wiki - https://github.com/demiurgosoft/dont-crush-my-castle/wiki\r\n\r\nWant to participate? Send an email to demiurgosoft@hotmail.com or just start coding in [GitHub](https://github.com/demiurgosoft/dont-crush-my-castle), remember to check the wiki section [Getting Started](https://github.com/demiurgosoft/dont-crush-my-castle/wiki/Getting%20Started)\r\n**This Project is Open-Source under GNU GPL v3**\r\n\r\n```\r\n  _______________________\r\n / Don't Crush my Castle \\\r\n \\ is a cool name        /\r\n  -----------------------\r\n         \\   ^__^\r\n          \\  (oo)\\_______\r\n             (__)\\       )\\/\\\r\n                 ||----w |\r\n                 ||     ||\r\n```\r\n\r\nDon't Crush My Castle Blog Content is under CC License\r\n\r\n<a rel=\"license\" href=\"http://creativecommons.org/licenses/by-nc-sa/4.0/\"><img alt=\"Creative Commons License\" style=\"border-width:0\" src=\"https://i.creativecommons.org/l/by-nc-sa/4.0/88x31.png\" /></a><br />This work is licensed under a <a rel=\"license\" href=\"http://creativecommons.org/licenses/by-nc-sa/4.0/\">Creative Commons Attribution-NonCommercial-ShareAlike 4.0 International License</a>.","google":"","note":"Don't delete this file! It's used internally to help with page regeneration."}